django_redis_data_manager/__init__.py
django_redis_data_manager/admin.py
django_redis_data_manager/apps.py
django_redis_data_manager/models.py
django_redis_data_manager/settings.py
django_redis_data_manager/tests.py
django_redis_data_manager/views.py
django_redis_data_manager/locale/zh_Hans/LC_MESSAGES/django.mo
django_redis_data_manager/locale/zh_Hans/LC_MESSAGES/django.po
django_redis_data_manager/migrations/0001_initial.py
django_redis_data_manager/migrations/__init__.py
django_redis_data_manager/static/django-redis-data-manager/django-redis-data-manager.css
django_redis_data_manager/static/django-redis-data-manager/django-redis-data-manager.js
django_redis_data_manager/templates/django-redis-data-manager/data-manager.html
django_redis_data_manager/templates/django-redis-data-manager/key-detail-table-hash.html
django_redis_data_manager/templates/django-redis-data-manager/key-detail-table-list.html
django_redis_data_manager/templates/django-redis-data-manager/key-detail-table-set.html
django_redis_data_manager/templates/django-redis-data-manager/key-detail-table-string.html
django_redis_data_manager/templates/django-redis-data-manager/namespace-detail-table.html
django_redis_data_manager_project/__init__.py
django_redis_data_manager_project/settings.py
django_redis_data_manager_project/urls.py
django_redis_data_manager_project/wsgi.conf.py
django_redis_data_manager_project/wsgi.ini
django_redis_data_manager_project/wsgi.py
django_redis_data_manager-0.1.8.dist-info/LICENSE
django_redis_data_manager-0.1.8.dist-info/METADATA
django_redis_data_manager-0.1.8.dist-info/WHEEL
django_redis_data_manager-0.1.8.dist-info/entry_points.txt
django_redis_data_manager-0.1.8.dist-info/top_level.txt
django_redis_data_manager-0.1.8.dist-info/RECORD
