Metadata-Version: 2.1
Name: django-redis-data-manager
Version: 0.1.8
Summary: A simple django application provide simple redis cache data manager functional.
Author: Qian WeiYong
Author-email: qianweiyong@zencore.cn
Maintainer: Qian WeiYong
Maintainer-email: qianweiyong@zencore.cn
License: MIT
Keywords: django simple application
Classifier: Development Status :: 5 - Production/Stable
Classifier: Intended Audience :: Developers
Classifier: Topic :: Software Development :: Libraries :: Python Modules
Classifier: License :: OSI Approved :: MIT License
Classifier: Programming Language :: Python :: 3
Classifier: Programming Language :: Python :: 3 :: Only
License-File: LICENSE
Requires-Dist: django
Requires-Dist: django-static-jquery3
Requires-Dist: django-static-fontawesome
Requires-Dist: django-server-controller
Requires-Dist: django-object-toolbar-admin
Requires-Dist: django-safe-fields
Requires-Dist: django-app-requires
Requires-Dist: redis
